odoo/addons/budget_control/README.rst
odoo/addons/budget_control/__init__.py
odoo/addons/budget_control/__manifest__.py
odoo/addons/budget_control/hooks.py
odoo/addons/budget_control/data/budget_data.xml
odoo/addons/budget_control/data/sequence_data.xml
odoo/addons/budget_control/demo/budget_template_demo.xml
odoo/addons/budget_control/models/__init__.py
odoo/addons/budget_control/models/account_budget_move.py
odoo/addons/budget_control/models/account_journal.py
odoo/addons/budget_control/models/account_move.py
odoo/addons/budget_control/models/account_move_line.py
odoo/addons/budget_control/models/analytic_account.py
odoo/addons/budget_control/models/base_budget_move.py
odoo/addons/budget_control/models/budget_balance_forward.py
odoo/addons/budget_control/models/budget_commit_forward.py
odoo/addons/budget_control/models/budget_constraint.py
odoo/addons/budget_control/models/budget_control.py
odoo/addons/budget_control/models/budget_kpi.py
odoo/addons/budget_control/models/budget_move_adjustment.py
odoo/addons/budget_control/models/budget_period.py
odoo/addons/budget_control/models/budget_plan.py
odoo/addons/budget_control/models/budget_template.py
odoo/addons/budget_control/models/budget_transfer.py
odoo/addons/budget_control/models/budget_transfer_item.py
odoo/addons/budget_control/models/res_company.py
odoo/addons/budget_control/models/res_config_settings.py
odoo/addons/budget_control/readme/CONTRIBUTORS.md
odoo/addons/budget_control/readme/DESCRIPTION.md
odoo/addons/budget_control/readme/USAGE.md
odoo/addons/budget_control/report/__init__.py
odoo/addons/budget_control/report/budget_common_monitoring.py
odoo/addons/budget_control/report/budget_monitor_report.py
odoo/addons/budget_control/report/budget_monitor_report_view.xml
odoo/addons/budget_control/report/budget_move_views.xml
odoo/addons/budget_control/security/analytic_security.xml
odoo/addons/budget_control/security/budget_adjustment_rules.xml
odoo/addons/budget_control/security/budget_control_rules.xml
odoo_addon_budget_control-18.0.1.4.4.dist-info/METADATA
odoo_addon_budget_control-18.0.1.4.4.dist-info/WHEEL
odoo_addon_budget_control-18.0.1.4.4.dist-info/top_level.txt
odoo_addon_budget_control-18.0.1.4.4.dist-info/RECORD
